uavgeo/__init__.py
uavgeo/compute/__init__.py
uavgeo/compute/chipping.py
uavgeo/compute/corrections.py
uavgeo/compute/indices.py
uavgeo/compute/products.py
uavgeo/datapipes/__init__.py
uavgeo/datapipes/yolo_pipe.py
uavgeo/load/__init__.py
uavgeo/load/download.py
uavgeo/load/importer.py
uavgeo-0.2.2.dist-info/LICENSE
uavgeo-0.2.2.dist-info/METADATA
uavgeo-0.2.2.dist-info/WHEEL
uavgeo-0.2.2.dist-info/top_level.txt
uavgeo-0.2.2.dist-info/RECORD
