Metadata-Version: 2.1
Name: uavgeo
Version: 0.2.2
Summary: UAV image processing library
Home-page: https://github.com/icaerus-eu/uavgeo/
Author: Jurrian Doornbos
Author-email: jurriandoornbos@gmail.com
Classifier: Programming Language :: Python :: 3
Classifier: Operating System :: OS Independent
Classifier: License :: OSI Approved :: GNU General Public License v3 (GPLv3)
Classifier: Topic :: Scientific/Engineering :: Artificial Intelligence
Classifier: Topic :: Scientific/Engineering :: GIS
Classifier: Topic :: Software Development :: Pre-processors
Requires-Python: >=3.9
License-File: LICENSE
Requires-Dist: geopandas >=0.13
Requires-Dist: rioxarray >=0.15
Requires-Dist: tqdm
Requires-Dist: geocube
Requires-Dist: rasterstats
Requires-Dist: scikit-learn
